alphabets/__init__.py
alphabets-0.1.dist-info/Licence.txt
alphabets-0.1.dist-info/METADATA
alphabets-0.1.dist-info/WHEEL
alphabets-0.1.dist-info/top_level.txt
alphabets-0.1.dist-info/RECORD
