Metadata-Version: 2.1
Name: alphabets
Version: 0.1
Summary: Ready To Use Alphabets an vowels in list and single line
Home-page: https://myprogramarchives.blogspot.com/2020/08/alphabets-module-in-python-by.html
Author: Aditya Shrivastava
Author-email: UNKNOWN
License: MIT
Platform: UNKNOWN
